geojson_client/__init__.py
geojson_client/__version__.py
geojson_client/consts.py
geojson_client/exceptions.py
geojson_client/feed_manager.py
geojson_client/generic_feed.py
geojson_client/usgs_earthquake_hazards_program_feed.py
geojson_client-0.8.dist-info/LICENSE
geojson_client-0.8.dist-info/METADATA
geojson_client-0.8.dist-info/WHEEL
geojson_client-0.8.dist-info/top_level.txt
geojson_client-0.8.dist-info/RECORD
