Metadata-Version: 2.1
Name: geojson-client
Version: 0.8
Summary: A GeoJSON client library.
Home-page: https://github.com/exxamalte/python-geojson-client
Author: Malte Franken
Author-email: coding@subspace.de
License: UNKNOWN
Platform: UNKNOWN
Classifier: Programming Language :: Python :: 3.7
Classifier: Programming Language :: Python :: 3.8
Classifier: Programming Language :: Python :: 3.9
Classifier: Programming Language :: Python :: 3.10
Classifier: License :: OSI Approved :: Apache Software License
Classifier: Operating System :: OS Independent
Requires-Dist: geojson (>=2.4.0)
Requires-Dist: haversine (>=1.0.1)
Requires-Dist: requests (>=2.20.0)
